README.md
setup.py
vodopad/__init__.py
vodopad/__main__.py
vodopad/dlib_face_identifier.py
vodopad/vodopad.py
vodopad.egg-info/PKG-INFO
vodopad.egg-info/SOURCES.txt
vodopad.egg-info/dependency_links.txt
vodopad.egg-info/entry_points.txt
vodopad.egg-info/requires.txt
vodopad.egg-info/top_level.txt