Metadata-Version: 1.0
Name: vodopad
Version: 0.1
Summary: Toolkit for managing photos
Home-page: UNKNOWN
Author: Dmitrii Topornin
Author-email: dtopornin@gmail.com
License: MIT
Platform: UNKNOWN
